ERLC/__init__.py
ERLC/erlc.py
ERLC/Classes/__init__.py
ERLC/Classes/client.py
ERLC/Classes/server.py
ERLC/Functions/__init__.py
ERLC/Functions/Server/__init__.py
ERLC/Functions/Server/getBans.py
ERLC/Functions/Server/getCmds.py
ERLC/Functions/Server/getJoins.py
ERLC/Functions/Server/getKills.py
ERLC/Functions/Server/getPlayers.py
ERLC/Functions/Server/getQueue.py
ERLC/Functions/Server/getStatus.py
ERLC/Functions/Server/requests.py
ERLC/Functions/Server/runCmd.py
Examples/__init__.py
Examples/bans.py
Examples/client.py
Examples/kills.py
Examples/players.py
Examples/status.py
ERLC-1.3.6.dist-info/METADATA
ERLC-1.3.6.dist-info/WHEEL
ERLC-1.3.6.dist-info/top_level.txt
ERLC-1.3.6.dist-info/RECORD
