Metadata-Version: 2.1
Name: ERLC
Version: 1.3.6
Summary: An API wrapper for the ERLC API
Author: mark.api
Classifier: Programming Language :: Python :: 3
Classifier: License :: OSI Approved :: MIT License
Classifier: Operating System :: OS Independent
Requires-Python: >=3.6
Requires-Dist: httpx
Requires-Dist: asyncio
